LICENSE
README.md
readme_.txt
setup.py
dmfq/__init__.py
dmfq/dmfq.py
dmfq/utils_imgs.py
dmfq/utils_train.py
dmfq.egg-info/PKG-INFO
dmfq.egg-info/SOURCES.txt
dmfq.egg-info/dependency_links.txt
dmfq.egg-info/requires.txt
dmfq.egg-info/top_level.txt
dmfq/utils/__init__.py