Metadata-Version: 1.0
Name: dmfq
Version: 0.0.3.2
Summary: dai ma fei qi
Home-page: https://pypi.org/project/docxt
Author: alex
Author-email: 371401439@qq.com
License: UNKNOWN
Platform: UNKNOWN
